estat_mcp_server/__init__.py
estat_mcp_server/server.py
estat_mcp_server-0.1.3.dist-info/METADATA
estat_mcp_server-0.1.3.dist-info/WHEEL
estat_mcp_server-0.1.3.dist-info/entry_points.txt
estat_mcp_server-0.1.3.dist-info/licenses/LICENSE
estat_mcp_server-0.1.3.dist-info/RECORD
