Metadata-Version: 2.4
Name: estat-mcp-server
Version: 0.1.3
Summary: MCP server for Japan's e-Stat API integration
Project-URL: Homepage, https://github.com/cygkichi/estat-mcp-server
Author-email: cygkichi <9675041+cygkichi@users.noreply.github.com>
License-File: LICENSE
Requires-Python: >=3.11
Requires-Dist: mcp>=1.6.0
